[{"family":"MaterialIcons","fonts":[{"asset":"fonts/MaterialIcons-Regular.otf"}]},{"family":"Helvetica","fonts":[{"weight":900,"asset":"fonts/Helvetica-Black.ttf"},{"weight":700,"asset":"fonts/Helvetica-Bold.ttf"},{"weight":300,"asset":"fonts/Helvetica-Light.ttf"},{"weight":500,"asset":"fonts/Helvetica-Medium.ttf"},{"weight":400,"asset":"fonts/Helvetica-regular.ttf"},{"weight":100,"asset":"fonts/Helvetica-Thin.ttf"}]},{"family":"packages/cupertino_icons/CupertinoIcons","fonts":[{"asset":"packages/cupertino_icons/assets/CupertinoIcons.ttf"}]}]